tiltify2/exceptions.py
tiltify2/tiltify.py
tiltify2-1.0.dist-info/DESCRIPTION.rst
tiltify2-1.0.dist-info/METADATA
tiltify2-1.0.dist-info/RECORD
tiltify2-1.0.dist-info/WHEEL
tiltify2-1.0.dist-info/metadata.json
tiltify2-1.0.dist-info/top_level.txt
