Metadata-Version: 2.0
Name: tiltify2
Version: 1.0
Summary: A wrapper for the 2nd version of the Tiltify API
Home-page: https://github.com/purrcat259/tiltify-v2-api-python
Author: Simon Agius Muscat
Author-email: simon@agius-muscat.net
License: MIT
Download-URL: https://github.com/purrcat259/tiltify-v2-api-python/archive/1.0.tar.gz
Keywords: tiltify,api,v2,livestreaming,charity,fundraising
Platform: UNKNOWN
